README.txt
setup.py
typelanguage/__init__.py
typelanguage/constraintgen.py
typelanguage/constraintsolve.py
typelanguage/enforce.py
typelanguage/lexer.py
typelanguage/parser.py
typelanguage/types.py
typelanguage.egg-info/PKG-INFO
typelanguage.egg-info/SOURCES.txt
typelanguage.egg-info/dependency_links.txt
typelanguage.egg-info/requires.txt
typelanguage.egg-info/top_level.txt