Metadata-Version: 1.0
Name: typelanguage
Version: 0.3
Summary: A type language for Python, including parsing, pretty-printing, type inference, type checking, and run-time contract enforcement.
Home-page: https://github.com/kennknowles/python-typelanguage
Author: Kenneth Knowles
Author-email: kenn.knowles@gmail.com
License: Apache 2.0
Platform: UNKNOWN
